methrafo/File.py
methrafo/__init__.py
methrafo/bamScripts.py
methrafo/download_genomes.py
methrafo/meth_predict.py
methrafo/meth_train.py
methrafo-1.0.1.data/data/model/rr.pkl
methrafo-1.0.1.dist-info/DESCRIPTION.rst
methrafo-1.0.1.dist-info/METADATA
methrafo-1.0.1.dist-info/RECORD
methrafo-1.0.1.dist-info/WHEEL
methrafo-1.0.1.dist-info/entry_points.txt
methrafo-1.0.1.dist-info/metadata.json
methrafo-1.0.1.dist-info/top_level.txt
