Metadata-Version: 2.0
Name: methrafo
Version: 1.0.1
Summary: MeDIP-Seq Methylation Level Random-forest based Estimator
Home-page: UNKNOWN
Author: Jun Ding
Author-email: jund@andrew.cmu.edu
License: MIT
Platform: UNKNOWN
Requires-Dist: scipy
Requires-Dist: numpy
Requires-Dist: scikit-learn
Requires-Dist: pyBigWig
